num2words/__init__.py
num2words/base.py
num2words/compat.py
num2words/currency.py
num2words/lang_AM.py
num2words/lang_AR.py
num2words/lang_CZ.py
num2words/lang_DE.py
num2words/lang_DK.py
num2words/lang_EN.py
num2words/lang_EN_IN.py
num2words/lang_EO.py
num2words/lang_ES.py
num2words/lang_ES_CO.py
num2words/lang_ES_NI.py
num2words/lang_ES_VE.py
num2words/lang_EU.py
num2words/lang_FA.py
num2words/lang_FI.py
num2words/lang_FR.py
num2words/lang_FR_BE.py
num2words/lang_FR_CH.py
num2words/lang_FR_DZ.py
num2words/lang_HE.py
num2words/lang_HU.py
num2words/lang_ID.py
num2words/lang_IT.py
num2words/lang_JA.py
num2words/lang_KN.py
num2words/lang_KO.py
num2words/lang_KZ.py
num2words/lang_LT.py
num2words/lang_LV.py
num2words/lang_NL.py
num2words/lang_NO.py
num2words/lang_PL.py
num2words/lang_PT.py
num2words/lang_PT_BR.py
num2words/lang_RO.py
num2words/lang_RU.py
num2words/lang_SL.py
num2words/lang_SR.py
num2words/lang_SV.py
num2words/lang_TE.py
num2words/lang_TG.py
num2words/lang_TH.py
num2words/lang_TR.py
num2words/lang_UK.py
num2words/lang_VI.py
num2words/utils.py
num2words-0.5.12.data/scripts/num2words
num2words-0.5.12.dist-info/COPYING
num2words-0.5.12.dist-info/METADATA
num2words-0.5.12.dist-info/WHEEL
num2words-0.5.12.dist-info/top_level.txt
num2words-0.5.12.dist-info/RECORD
