Metadata-Version: 2.1
Name: num2words
Version: 0.5.12
Summary: Modules to convert numbers to words. Easily extensible.
Home-page: https://github.com/savoirfairelinux/num2words
Author: Taro Ogawa <tso at users sourceforge net>
Author-email: tos@users.sourceforge.net
Maintainer: Savoir-faire Linux inc.
Maintainer-email: support@savoirfairelinux.com
License: LGPL
Keywords: number word numbers words convert conversion i18n localisation localization internationalisation internationalization
Classifier: Development Status :: 5 - Production/Stable
Classifier: Intended Audience :: Developers
Classifier: License :: OSI Approved :: GNU Library or Lesser General Public License (LGPL)
Classifier: Programming Language :: Python :: 3.6
Classifier: Programming Language :: Python :: 3.7
Classifier: Programming Language :: Python :: 3.8
Classifier: Programming Language :: Python :: 3.9
Classifier: Programming Language :: Python :: 3.10
Classifier: Topic :: Software Development :: Internationalization
Classifier: Topic :: Software Development :: Libraries :: Python Modules
Classifier: Topic :: Software Development :: Localization
Classifier: Topic :: Text Processing :: Linguistic
License-File: COPYING
